setup.py
frc3223_azurite/__init__.py
frc3223_azurite/conversions.py
frc3223_azurite/data.py
frc3223_azurite/inertials.py
frc3223_azurite/motors.py
frc3223_azurite/pidcontroller.py
frc3223_azurite.egg-info/PKG-INFO
frc3223_azurite.egg-info/SOURCES.txt
frc3223_azurite.egg-info/dependency_links.txt
frc3223_azurite.egg-info/top_level.txt