Metadata-Version: 1.1
Name: frc3223-azurite
Version: 0.0.6
Summary: miscellaneous utilities for jupyter notebooks
Home-page: https://github.com/Retro3223/azurite
Author: Ellery Newcomer
Author-email: ellery-newcomer@utulsa.edu
License: UNKNOWN
Platform: UNKNOWN
Classifier: Programming Language :: Python :: 3.6
